pingpoint/__init__.py
pingpoint/cli.py
pingpoint/dns_checker.py
pingpoint/http_checker.py
pingpoint/ssl_checker.py
pingpoint-1.0.2.dist-info/METADATA
pingpoint-1.0.2.dist-info/WHEEL
pingpoint-1.0.2.dist-info/entry_points.txt
pingpoint-1.0.2.dist-info/top_level.txt
pingpoint-1.0.2.dist-info/RECORD
