Metadata-Version: 2.4
Name: pingpoint
Version: 1.0.2
Summary: A fast CLI tool for HTTP, DNS, and SSL diagnostics
Home-page: https://github.com/ImZackAdams/pingpoint
Author: Zack Adams
Author-email: imZackAdams@protonmail.com
Classifier: Programming Language :: Python :: 3
Classifier: License :: OSI Approved :: MIT License
Classifier: Operating System :: OS Independent
Classifier: Environment :: Console
Classifier: Intended Audience :: Developers
Classifier: Topic :: Internet :: WWW/HTTP
Classifier: Topic :: System :: Networking :: Monitoring
Requires-Python: >=3.6
Requires-Dist: click
Requires-Dist: requests
Dynamic: author
Dynamic: author-email
Dynamic: classifier
Dynamic: description
Dynamic: description-content-type
Dynamic: home-page
Dynamic: requires-dist
Dynamic: requires-python
Dynamic: summary
